[
    {
        "image": [
            "//assetsprx.matchesfashion.com/img/product/1454160_1_medium.jpg"
        ],
        "name": "Fringed checked wool-blend coat",
        "designer": "Marni",
        "url": "/products/Marni-Fringed-checked-wool-blend-coat-1454160",
        "price": "£1,790",
        "index": 0,
        "code": "1454160"
    },
    {
        "image": [
            "//assetsprx.matchesfashion.com/img/product/1454112_1_medium.jpg"
        ],
        "name": "Shopping logo-jacquard tote bag &amp; leather pouch",
        "designer": "Marni",
        "url": "/products/Marni-Shopping-logo-jacquard-tote-bag-%26-leather-pouch-1454112",
        "price": "£890",
        "index": 1,
        "code": "1454112"
    },
    {
        "image": [
            "//assetsprx.matchesfashion.com/img/product/1454159_1_medium.jpg"
        ],
        "name": "Suede and silk-knit midi skirt",
        "designer": "Marni",
        "url": "/products/Marni-Suede-and-silk-knit-midi-skirt-1454159",
        "price": "£1,690",
        "index": 2,
        "code": "1454159"
    },
    {
        "image": [
            "//assetsprx.matchesfashion.com/img/product/1454108_1_medium.jpg"
        ],
        "name": "Gathered-leather platform clogs",
        "designer": "Marni",
        "url": "/products/Marni-Gathered-leather-platform-clogs-1454108",
        "price": "£750",
        "index": 3,
        "code": "1454108"
    },
    {
        "image": [
            "//assetsprx.matchesfashion.com/img/product/1474365_1_medium.jpg"
        ],
        "name": "Rainbow diamond, enamel &amp; 18kt gold ring",
        "designer": "Bea Bongiasca",
        "url": "/products/Bea-Bongiasca-Rainbow-diamond%2C-enamel-%26-18kt-gold-ring-1474365",
        "price": "£6,330",
        "index": 4,
        "code": "1474365"
    },
    {
        "image": [
            "//assetsprx.matchesfashion.com/img/product/1457993_1_medium.jpg"
        ],
        "name": "Linear-print denim jacket",
        "designer": "Ahluwalia",
        "url": "/products/Ahluwalia-Linear-print-denim-jacket-1457993",
        "price": "£440",
        "index": 5,
        "code": "1457993"
    },
    {
        "image": [
            "//assetsprx.matchesfashion.com/img/product/1454847_1_medium.jpg"
        ],
        "name": "Cubi small Anagram-jacquard canvas and leather bag",
        "designer": "Loewe",
        "url": "/products/Loewe-Cubi-small-Anagram-jacquard-canvas-and-leather-bag-1454847",
        "price": "£850",
        "index": 6,
        "code": "1454847"
    },
    {
        "image": [
            "//assetsprx.matchesfashion.com/img/product/1458005_1_medium.jpg"
        ],
        "name": "Laser-print wide-leg jeans",
        "designer": "Ahluwalia",
        "url": "/products/Ahluwalia-Laser-print-wide-leg-jeans-1458005",
        "price": "£370",
        "index": 7,
        "code": "1458005"
    },
    {
        "image": [
            "//assetsprx.matchesfashion.com/img/product/1462934_1_medium.jpg"
        ],
        "name": "Rib-knitted cashmere cardigan",
        "designer": "The Elder Statesman",
        "url": "/products/The-Elder-Statesman-Rib-knitted-cashmere-cardigan-1462934",
        "price": "£865",
        "index": 8,
        "code": "1462934"
    },
    {
        "image": [
            "//assetsprx.matchesfashion.com/img/product/1438048_1_medium.jpg"
        ],
        "name": "Pleated leather bracelet bag",
        "designer": "Loewe",
        "url": "/products/Loewe-Pleated-leather-bracelet-bag-1438048",
        "price": "£1,000",
        "index": 9,
        "code": "1438048"
    },
    {
        "image": [
            "//assetsprx.matchesfashion.com/img/product/1462935_1_medium.jpg"
        ],
        "name": "High-rise ribbed-cashmere trousers",
        "designer": "The Elder Statesman",
        "url": "/products/The-Elder-Statesman-High-rise-ribbed-cashmere-trousers-1462935",
        "price": "£1,025",
        "index": 10,
        "code": "1462935"
    },
    {
        "image": [
            "//assetsprx.matchesfashion.com/img/product/1461225_1_medium.jpg"
        ],
        "name": "XL Link mismatched drop earrings",
        "designer": "Paco Rabanne",
        "url": "/products/Paco-Rabanne-XL-Link-mismatched-drop-earrings-1461225",
        "price": "£300",
        "index": 11,
        "code": "1461225"
    },
    {
        "image": [
            "//assetsprx.matchesfashion.com/img/product/1454846_1_medium.jpg"
        ],
        "name": "Cubi small Anagram-jacquard canvas and leather bag",
        "designer": "Loewe",
        "url": "/products/Loewe-Cubi-small-Anagram-jacquard-canvas-and-leather-bag-1454846",
        "price": "£850",
        "index": 12,
        "code": "1454846"
    },
    {
        "image": [
            "//assetsprx.matchesfashion.com/img/product/1439381_1_medium.jpg"
        ],
        "name": "Josie cutout-back matelassé top",
        "designer": "Cecilie Bahnsen",
        "url": "/products/Cecilie-Bahnsen-Josie-cutout-back-matelass%C3%A9-top-1439381",
        "price": "£660",
        "index": 13,
        "code": "1439381"
    },
    {
        "image": [
            "//assetsprx.matchesfashion.com/img/product/1383839_1_medium.jpg"
        ],
        "name": "Knife Edge diamond &amp; 18kt gold bracelet",
        "designer": "Lizzie Mandler",
        "url": "/products/Lizzie-Mandler-Knife-Edge-diamond-%26-18kt-gold-bracelet-1383839",
        "price": "£4,160",
        "index": 14,
        "code": "1383839"
    },
    {
        "image": [
            "//assetsprx.matchesfashion.com/img/product/1444750_1_medium.jpg"
        ],
        "name": "Daisy flared-leg jeans",
        "designer": "Wandler",
        "url": "/products/Wandler-Daisy-flared-leg-jeans-1444750",
        "price": "£190",
        "index": 15,
        "code": "1444750"
    },
    {
        "image": [
            "//assetsprx.matchesfashion.com/img/product/1350798_1_medium.jpg"
        ],
        "name": "Knife Edge diamond &amp; 18kt gold ring",
        "designer": "Lizzie Mandler",
        "url": "/products/Lizzie-Mandler-Knife-Edge-diamond-%26-18kt-gold-ring-1350798",
        "price": "£9,130",
        "index": 16,
        "code": "1350798"
    },
    {
        "image": [
            "//assetsprx.matchesfashion.com/img/product/1462490_1_medium.jpg"
        ],
        "name": "Striped-jersey maxi dress",
        "designer": "Carolina Herrera",
        "url": "/products/Carolina-Herrera-Striped-jersey-maxi-dress-1462490",
        "price": "£1,330",
        "index": 17,
        "code": "1462490"
    },
    {
        "image": [
            "//assetsprx.matchesfashion.com/img/product/1455431_1_medium.jpg"
        ],
        "name": "Demi leather and gathered-satin slides",
        "designer": "Malone Souliers",
        "url": "/products/Malone-Souliers-Demi-leather-and-gathered-satin-slides-1455431",
        "price": "£395",
        "index": 18,
        "code": "1455431"
    },
    {
        "image": [
            "//assetsprx.matchesfashion.com/img/product/1475250_1_medium.jpg"
        ],
        "name": "GG-logo crystal-embellished headband",
        "designer": "Gucci",
        "url": "/products/Gucci-GG-logo-crystal-embellished-headband-1475250",
        "price": "£315",
        "index": 19,
        "code": "1475250"
    },
    {
        "image": [
            "//assetsprx.matchesfashion.com/img/product/1461913_1_medium.jpg"
        ],
        "name": "Geometric-jacquard sweater",
        "designer": "Paco Rabanne",
        "url": "/products/Paco-Rabanne-Geometric-jacquard-sweater-1461913",
        "price": "£710",
        "index": 20,
        "code": "1461913"
    },
    {
        "image": [
            "//assetsprx.matchesfashion.com/img/product/1460938_1_medium.jpg"
        ],
        "name": "Pixel chainmail tote bag",
        "designer": "Paco Rabanne",
        "url": "/products/Paco-Rabanne-Pixel-chainmail-tote-bag-1460938",
        "price": "£890",
        "index": 21,
        "code": "1460938"
    },
    {
        "image": [
            "//assetsprx.matchesfashion.com/img/product/1461914_1_medium.jpg"
        ],
        "name": "Geometric-jacquard flare-leg trousers",
        "designer": "Paco Rabanne",
        "url": "/products/Paco-Rabanne-Geometric-jacquard-flare-leg-trousers-1461914",
        "price": "£800",
        "index": 22,
        "code": "1461914"
    },
    {
        "image": [
            "//assetsprx.matchesfashion.com/img/product/1461931_1_medium.jpg"
        ],
        "name": "Cropped monogram-print jersey T-shirt",
        "designer": "Paco Rabanne",
        "url": "/products/Paco-Rabanne-Cropped-monogram-print-jersey-T-shirt-1461931",
        "price": "£190",
        "index": 23,
        "code": "1461931"
    }
]
